README.md
setup.py
src/vdk/plugin/audit/audit_config.py
src/vdk/plugin/audit/audit_plugin.py
src/vdk_audit.egg-info/PKG-INFO
src/vdk_audit.egg-info/SOURCES.txt
src/vdk_audit.egg-info/dependency_links.txt
src/vdk_audit.egg-info/entry_points.txt
src/vdk_audit.egg-info/requires.txt
src/vdk_audit.egg-info/top_level.txt